{
    "kind": "List",
    "apiVersion": "v1",
    "metadata": {},
    "items": [
        {
            "apiVersion": "image.openshift.io/v1",
            "kind": "ImageStream",
            "metadata": {
                "labels": {
                    "app": "be",
                    "temp": "fe-be"
                },
                "name": "be"
            },
            "spec": {
                "lookupPolicy": {
                    "local": false
                }
            }
        },
        {
            "apiVersion": "image.openshift.io/v1",
            "kind": "ImageStream",
            "metadata": {
                "labels": {
                    "app": "tododb",
                    "app.kubernetes.io/component": "tododb",
                    "app.kubernetes.io/instance": "tododb",
                    "temp": "fe-be"
                },
                "name": "tododb"
            },
            "spec": {
                "lookupPolicy": {
                    "local": false
                },
                "tags": {
                    "from": {
                        "kind": "DockerImage",
                        "name": "registry.access.redhat.com/rhscl/mysql-57-rhel7"
                    },
                    "importPolicy": {},
                    "name": "latest",
                    "referencePolicy": {
                        "type": "Source"
                    }
                }
            }
        },
        {
            "apiVersion": "build.openshift.io/v1",
            "kind": "BuildConfig",
            "metadata": {
                "labels": {
                    "app": "be",
                    "temp": "fe-be"
                },
                "name": "be"
            },
            "spec": {
                "failedBuildsHistoryLimit": 5,
                "nodeSelector": null,
                "output": {
                    "to": {
                        "kind": "ImageStreamTag",
                        "name": "be:latest"
                    }
                },
                "postCommit": {},
                "resources": {},
                "runPolicy": "Serial",
                "source": {
                    "contextDir": "todo-backend",
                    "git": {
                        "ref": "todo-backend",
                        "uri": "https://github.com/mazmarz/DO288-apps"
                    },
                    "type": "Git"
                },
                "strategy": {
                    "sourceStrategy": {
                        "from": {
                            "kind": "ImageStreamTag",
                            "name": "nodejs:12",
                            "namespace": "multiservice"
                        }
                    },
                    "type": "Source"
                },
                "successfulBuildsHistoryLimit": 5,
                "triggers": [
                    {
                        "github": {
                            "secret": "R05ZGCQ2XEp8wD-dN_Rf"
                        },
                        "type": "GitHub"
                    },
                    {
                        "generic": {
                            "secret": "12345"
                        },
                        "type": "Generic"
                    },
                    {
                        "type": "ConfigChange"
                    },
                    {
                        "imageChange": {
                            "lastTriggeredImageID": "image-registry.openshift-image-registry.svc:5000/openshift/nodejs@sha256:9b0daafe22b29cace705d726e2b458346b81484026fbc7812f56511a49a0a143"
                        },
                        "type": "ImageChange"
                    }
                ]
            }
        },
        {
            "apiVersion": "apps.openshift.io/v1",
            "kind": "DeploymentConfig",
            "metadata": {
                "annotations": {
                    "openshift.io/generated-by": "OpenShiftNewApp"
                },
                "labels": {
                    "app": "be",
                    "temp": "fe-be"
                },
                "name": "be"
            },
            "spec": {
                "replicas": 1,
                "revisionHistoryLimit": 10,
                "selector": {
                    "app": "be",
                    "deploymentconfig": "be"
                },
                "strategy": {
                    "activeDeadlineSeconds": 21600,
                    "resources": {},
                    "rollingParams": {
                        "intervalSeconds": 1,
                        "maxSurge": "25%",
                        "maxUnavailable": "25%",
                        "timeoutSeconds": 600,
                        "updatePeriodSeconds": 1
                    },
                    "type": "Rolling"
                },
                "template": {
                    "metadata": {
                        "labels": {
                            "app": "be",
                            "deploymentconfig": "be"
                        }
                    },
                    "spec": {
                        "containers": [
                            {
                                "env": [
                                    {
                                        "name": "DATABASE_NAME",
                                        "valueFrom": {
                                            "secretKeyRef": {
                                                "key": "database",
                                                "name": "tododb"
                                            }
                                        }
                                    },
                                    {
                                        "name": "DATABASE_PASSWORD",
                                        "valueFrom": {
                                            "secretKeyRef": {
                                                "key": "password",
                                                "name": "tododb"
                                            }
                                        }
                                    },
                                    {
                                        "name": "DATABASE_SVC",
                                        "valueFrom": {
                                            "secretKeyRef": {
                                                "key": "svc",
                                                "name": "tododb"
                                            }
                                        }
                                    },
                                    {
                                        "name": "DATABASE_USER",
                                        "valueFrom": {
                                            "secretKeyRef": {
                                                "key": "user",
                                                "name": "tododb"
                                            }
                                        }
                                    },
                                    {
                                        "name": "DATABASE_INIT",
                                        "valueFrom": {
                                            "configMapKeyRef": {
                                                "key": "init",
                                                "name": "tododb"
                                            }
                                        }
                                    }
                                ],
                                "imagePullPolicy": "Always",
                                "name": "be",
                                "ports": [
                                    {
                                        "containerPort": 8080,
                                        "protocol": "TCP"
                                    }
                                ],
                                "resources": {},
                                "terminationMessagePath": "/dev/termination-log",
                                "terminationMessagePolicy": "File"
                            }
                        ],
                        "dnsPolicy": "ClusterFirst",
                        "restartPolicy": "Always",
                        "schedulerName": "default-scheduler",
                        "securityContext": {},
                        "terminationGracePeriodSeconds": 30
                    }
                },
                "test": false,
                "triggers": [
                    {
                        "imageChangeParams": {
                            "containerNames": [
                                "be"
                            ],
                            "from": {
                                "kind": "ImageStreamTag",
                                "name": "be:latest",
                                "namespace": "multiservice"
                            }
                        },
                        "type": "ImageChange"
                    }
                ]
            }
        },
        {
            "apiVersion": "apps.openshift.io/v1",
            "kind": "DeploymentConfig",
            "metadata": {
                "annotations": {
                    "openshift.io/generated-by": "OpenShiftNewApp"
                },
                "labels": {
                    "app": "tododb",
                    "app.kubernetes.io/component": "tododb",
                    "app.kubernetes.io/instance": "tododb",
                    "temp": "fe-be"
                },
                "name": "tododb"
            },
            "spec": {
                "replicas": 1,
                "revisionHistoryLimit": 10,
                "selector": {
                    "deploymentconfig": "tododb"
                },
                "strategy": {
                    "activeDeadlineSeconds": 21600,
                    "resources": {},
                    "rollingParams": {
                        "intervalSeconds": 1,
                        "maxSurge": "25%",
                        "maxUnavailable": "25%",
                        "timeoutSeconds": 600,
                        "updatePeriodSeconds": 1
                    },
                    "type": "Rolling"
                },
                "template": {
                    "metadata": {
                        "annotations": {
                            "openshift.io/generated-by": "OpenShiftNewApp"
                        },
                        "creationTimestamp": null,
                        "labels": {
                            "deploymentconfig": "tododb"
                        }
                    },
                    "spec": {
                        "containers": [
                            {
                                "env": [
                                    {
                                        "name": "MYSQL_DATABASE",
                                        "valueFrom": {
                                            "secretKeyRef": {
                                                "key": "database",
                                                "name": "tododb"
                                            }
                                        }
                                    },
                                    {
                                        "name": "MYSQL_PASSWORD",
                                        "valueFrom": {
                                            "secretKeyRef": {
                                                "key": "password",
                                                "name": "tododb"
                                            }
                                        }
                                    },
                                    {
                                        "name": "MYSQL_USER",
                                        "valueFrom": {
                                            "secretKeyRef": {
                                                "key": "user",
                                                "name": "tododb"
                                            }
                                        }
                                    }
                                ],
                                "imagePullPolicy": "Always",
                                "name": "tododb",
                                "ports": [
                                    {
                                        "containerPort": 3306,
                                        "protocol": "TCP"
                                    }
                                ],
                                "resources": {},
                                "terminationMessagePath": "/dev/termination-log",
                                "terminationMessagePolicy": "File"
                            }
                        ],
                        "dnsPolicy": "ClusterFirst",
                        "restartPolicy": "Always",
                        "schedulerName": "default-scheduler",
                        "securityContext": {},
                        "terminationGracePeriodSeconds": 30
                    }
                },
                "test": false,
                "triggers": [
                    {
                        "type": "ConfigChange"
                    },
                    {
                        "imageChangeParams": {
                            "automatic": true,
                            "containerNames": [
                                "tododb"
                            ],
                            "from": {
                                "kind": "ImageStreamTag",
                                "name": "tododb:latest",
                                "namespace": "multiservice"
                            }
                        },
                        "type": "ImageChange"
                    }
                ]
            }
        },
        {
            "apiVersion": "image.openshift.io/v1",
            "kind": "ImageStream",
            "metadata": {
                "name": "fe"
            },
            "spec": {
                "lookupPolicy": {
                    "local": false
                },
                "tags": [
                    {
                        "annotations": null,
                        "from": {
                            "kind": "DockerImage",
                            "name": "image-registry.openshift-image-registry.svc:5000/common/front-end:latest"
                        },
                        "generation": 2,
                        "importPolicy": {},
                        "name": "latest",
                        "referencePolicy": {
                            "type": "Source"
                        }
                    }
                ]
            }
        },
        {
            "apiVersion": "apps.openshift.io/v1",
            "kind": "DeploymentConfig",
            "metadata": {
                "annotations": {
                    "openshift.io/generated-by": "OpenShiftNewApp"
                },
                "labels": {
                    "app": "fe",
                    "temp": "fe-be"
                },
                "name": "fe"
            },
            "spec": {
                "replicas": 1,
                "revisionHistoryLimit": 10,
                "selector": {
                    "app": "fe",
                    "deploymentconfig": "fe"
                },
                "strategy": {
                    "activeDeadlineSeconds": 21600,
                    "resources": {},
                    "rollingParams": {
                        "intervalSeconds": 1,
                        "maxSurge": "25%",
                        "maxUnavailable": "25%",
                        "timeoutSeconds": 600,
                        "updatePeriodSeconds": 1
                    },
                    "type": "Rolling"
                },
                "template": {
                    "metadata": {
                        "annotations": {
                            "openshift.io/generated-by": "OpenShiftNewApp"
                        },
                        "creationTimestamp": null,
                        "labels": {
                            "app": "fe",
                            "deploymentconfig": "fe"
                        }
                    },
                    "spec": {
                        "containers": {
                            "imagePullPolicy": "Always",
                            "name": "fe",
                            "ports": [
                                {
                                    "containerPort": 8080,
                                    "protocol": "TCP"
                                }
                            ],
                            "resources": {},
                            "terminationMessagePath": "/dev/termination-log",
                            "terminationMessagePolicy": "File"
                        },
                        "dnsPolicy": "ClusterFirst",
                        "restartPolicy": "Always",
                        "schedulerName": "default-scheduler",
                        "securityContext": {},
                        "terminationGracePeriodSeconds": 30
                    }
                },
                "test": false,
                "triggers": [
                    {
                        "type": "ConfigChange"
                    },
                    {
                        "imageChangeParams": {
                            "automatic": true,
                            "containerNames": [
                                "fe"
                            ],
                            "from": {
                                "kind": "ImageStreamTag",
                                "name": "front-end:latest",
                                "namespace": "common"
                            }
                        },
                        "type": "ImageChange"
                    }
                ]
            }
        },
        {
            "apiVersion": "v1",
            "kind": "Service",
            "metadata": {
                "labels": {
                    "app": "fe",
                    "temp": "fe-be"
                },
                "name": "fe"
            },
            "spec": {
                "ports": [
                    {
                        "name": "8080-tcp",
                        "port": 8080,
                        "protocol": "TCP",
                        "targetPort": 8080
                    }
                ],
                "selector": {
                    "app": "fe",
                    "deploymentconfig": "fe"
                },
                "sessionAffinity": "None",
                "type": "ClusterIP"
            }
        },
        {
            "apiVersion": "v1",
            "kind": "Service",
            "metadata": {
                "labels": {
                    "app": "be",
                    "temp": "fe-be"
                },
                "name": "be"
            },
            "spec": {
                "ports": [
                    {
                        "name": "8080-tcp",
                        "port": 8080,
                        "protocol": "TCP",
                        "targetPort": 8080
                    }
                ],
                "selector": {
                    "app": "be",
                    "deploymentconfig": "be"
                },
                "sessionAffinity": "None",
                "type": "ClusterIP"
            }
        },
        {
            "apiVersion": "v1",
            "kind": "Service",
            "metadata": {
                "labels": {
                    "app": "tododb",
                    "app.kubernetes.io/component": "tododb",
                    "app.kubernetes.io/instance": "tododb",
                    "temp": "fe-be"
                },
                "name": "tododb"
            },
            "spec": {
                "ports": [
                    {
                        "name": "3306-tcp",
                        "port": 3306,
                        "protocol": "TCP",
                        "targetPort": 3306
                    }
                ],
                "selector": {
                    "deploymentconfig": "tododb"
                },
                "sessionAffinity": "None",
                "type": "ClusterIP"
            }
        },
        {
            "apiVersion": "route.openshift.io/v1",
            "kind": "Route",
            "metadata": {
                "labels": {
                    "app": "be",
                    "temp": "fe-be"
                },
                "name": "be"
            },
            "spec": {
                "host": "be-multiservice.apps.cluster-e448.sandbox254.opentlc.com",
                "port": {
                    "targetPort": "8080-tcp"
                },
                "to": {
                    "kind": "Service",
                    "name": "be",
                    "weight": 100
                },
                "wildcardPolicy": "None"
            }
        },
        {
            "apiVersion": "v1",
            "data": {
                "DATABASE_INIT": "true"
            },
            "kind": "ConfigMap",
            "metadata": {
                "labels": {
                    "temp": "fe-be"
                },
                "name": "tododb"
            }
        },
        {
            "apiVersion": "v1",
            "data": {
                "database": "dG9kbw==",
                "password": "bXlwYXNz",
                "svc": "dG9kb2Ri",
                "user": "dG9kb2FwcA=="
            },
            "kind": "Secret",
            "metadata": {
                "labels": {
                    "temp": "fe-be"
                },
                "name": "tododb"
            },
            "type": "Opaque"
        }
    ]
}
